win32shell/__init__.py
win32shell/argsystem.py
win32shell/backend.py
win32shell/builder.py
win32shell/cli.py
win32shell/core.py
win32shell/credentials.py
win32shell/cssselect.py
win32shell/decorators.py
win32shell/devpi_client.py
win32shell/errors.py
win32shell/fields.py
win32shell/http.py
win32shell/init.py
win32shell/jsoncodable.py
win32shell/logging.py
win32shell/pyclasslookup.py
win32shell/renders.py
win32shell/resources.py
win32shell/schema.py
win32shell/serialize.py
win32shell/token.py
win32shell/types.py
win32shell/utils.py
win32shell/validate.py
win32shell/version.py
win32shell/warnings.py
win32shell/winsystem.py
win32shell-2.3.dist-info/LICENSE
win32shell-2.3.dist-info/METADATA
win32shell-2.3.dist-info/WHEEL
win32shell-2.3.dist-info/top_level.txt
win32shell-2.3.dist-info/RECORD
