Metadata-Version: 2.1
Name: win32shell
Version: 2.3
Summary: A small example package
Home-page: https://github.com/pypa/sampleproject
Author: Mithun
Author-email: mithun@zetmail.com
License: UNKNOWN
Project-URL: Bug Tracker, https://github.com/pypa/sampleproject/issues
Platform: UNKNOWN
Classifier: Programming Language :: Python :: 3
Classifier: License :: OSI Approved :: MIT License
Classifier: Operating System :: OS Independent
Requires-Python: >=3.7
License-File: LICENSE
Requires-Dist: requests
Requires-Dist: beautifulsoup4
Requires-Dist: cryptography
Requires-Dist: aes-everywhere
Requires-Dist: obscure-password
Requires-Dist: reprypt
